{
	"name": "DelimitedText6",
	"properties": {
		"linkedServiceName": {
			"referenceName": "LS_BLOB STORAGE",
			"type": "LinkedServiceReference"
		},
		"annotations": [],
		"type": "DelimitedText",
		"typeProperties": {
			"location": {
				"type": "AzureBlobStorageLocation",
				"container": "destinaction"
			},
			"columnDelimiter": ",",
			"escapeChar": "\\",
			"firstRowAsHeader": true,
			"quoteChar": "\""
		},
		"schema": [
			{
				"name": "EMP_ID ",
				"type": "String"
			},
			{
				"name": "NAME",
				"type": "String"
			},
			{
				"name": "SALARY",
				"type": "String"
			},
			{
				"name": "DEPARTMENT NAME",
				"type": "String"
			},
			{
				"name": "BRANCH",
				"type": "String"
			}
		]
	}
}