{
	"name": "integrationRuntime1",
	"properties": {
		"type": "Managed",
		"typeProperties": {
			"computeProperties": {
				"location": "Central India",
				"nodeSize": "Standard_D8_v3",
				"numberOfNodes": 2,
				"maxParallelExecutionsPerNode": 8
			},
			"ssisProperties": {
				"catalogInfo": {
					"catalogServerEndpoint": "sqladftraining1.database.windows.net",
					"catalogPricingTier": "S1"
				},
				"edition": "Standard",
				"runtimeVersion": "2017",
				"licenseType": "LicenseIncluded"
			}
		}
	}
}